{
 "sections": [
  {
   "id": "6c05fb9e-6f9b-9bd3-c55e-ad42b4a8bfda",
   "title": "Introduction",
   "files": [
    {
     "path": "#tabs",
     "action": "close"
    }
   ],
   "layout": "1-panel",
   "path": [],
   "type": "markdown",
   "content-file": ".guides/content/Introduction-6c05.md",
   "chapter": true,
   "reset": [],
   "teacherOnly": false
  },
  {
   "id": "f8badccb-a5a7-1480-fc93-becd4f92513a",
   "title": "Script tags",
   "files": [
    {
     "path": "#tabs",
     "action": "close"
    },
    {
     "path": "script-tags/index.html",
     "panel": 0,
     "action": "open"
    },
    {
     "path": "#preview: script-tags/index.html",
     "panel": 1,
     "action": "open"
    }
   ],
   "layout": "3-cell",
   "path": [
    "script-tags"
   ],
   "type": "markdown",
   "content-file": ".guides/content/Script-tags-f8ba.md",
   "chapter": true,
   "reset": [
    "script-tags"
   ],
   "teacherOnly": false
  },
  {
   "id": "e20f6506-4ac5-1a71-5720-3706608cd34b",
   "title": "Your first script",
   "files": [],
   "layout": "",
   "path": [
    "script-tags"
   ],
   "type": "markdown",
   "content-file": ".guides/content/Your-first-script-e20f.md",
   "chapter": false,
   "reset": [],
   "teacherOnly": false
  },
  {
   "id": "60a31bc5-e73c-cb6b-e997-e0d8ed134e05",
   "title": "Writing to the console",
   "files": [
    {
     "path": "#tabs",
     "action": "close"
    },
    {
     "path": "#preview: console-log/example.html",
     "panel": 1,
     "action": "open"
    },
    {
     "path": "console-log/example.html",
     "panel": 0,
     "ref": "console.log",
     "lineCount": null,
     "action": "open"
    }
   ],
   "layout": "",
   "path": [
    "console-log"
   ],
   "type": "markdown",
   "content-file": ".guides/content/Writing-to-the-console-60a3.md",
   "chapter": true,
   "reset": [
    "console-log"
   ],
   "teacherOnly": false
  },
  {
   "id": "cc84338a-1990-6a0e-6d0c-405586ef47",
   "title": "Debugging JS code",
   "files": [
    {
     "path": "#tabs",
     "action": "close"
    },
    {
     "path": "debugger/example.html",
     "panel": 0,
     "action": "open"
    }
   ],
   "layout": "2-panels",
   "path": [
    "debugger"
   ],
   "type": "markdown",
   "content-file": ".guides/content/Debugging-JS-code-cc84.md",
   "chapter": true,
   "reset": [],
   "teacherOnly": false
  },
  {
   "id": "e20d742-8e3e-4ddc-c3aa-a4776af666f3",
   "title": "Debugger challenge",
   "files": [
    {
     "path": "#tabs",
     "action": "close"
    }
   ],
   "layout": "1-panel",
   "path": [],
   "type": "markdown",
   "content-file": ".guides/content/Debugger-challenge-e20d.md",
   "chapter": false,
   "reset": [],
   "teacherOnly": false
  },
  {
   "id": "ee3e90ab-2d05-ddf3-dccc-e4b78d603e2c",
   "title": "Clock example",
   "files": [
    {
     "path": "#tabs",
     "action": "close"
    },
    {
     "path": "clock/index-console.html",
     "panel": 0,
     "action": "open"
    },
    {
     "path": "#preview: clock/index-console.html",
     "panel": 1,
     "action": "open"
    }
   ],
   "layout": "3-cell",
   "path": [
    "clock"
   ],
   "type": "markdown",
   "content-file": ".guides/content/Clock-example-ee3e.md",
   "chapter": true,
   "reset": [
    "clock"
   ],
   "teacherOnly": false
  },
  {
   "id": "dc3b907-799-1c3a-ff03-6d0dafbe95a4",
   "title": "Clock example (2)",
   "files": [
    {
     "path": "#tabs",
     "action": "close"
    },
    {
     "path": "clock/index.html",
     "panel": 0,
     "action": "open"
    },
    {
     "path": "#preview: clock/index.html",
     "panel": 1,
     "action": "open"
    }
   ],
   "layout": "",
   "path": [
    "clock"
   ],
   "type": "markdown",
   "content-file": ".guides/content/Clock-example--2--dc3b.md",
   "chapter": false,
   "reset": [],
   "teacherOnly": false
  },
  {
   "id": "150172b9-e745-5d35-ca66-f578813ec02c",
   "title": "Document ready",
   "files": [
    {
     "path": "#tabs",
     "action": "close"
    },
    {
     "path": "document-ready/example1.html",
     "panel": 0,
     "action": "open"
    },
    {
     "path": "#preview: document-ready/example1.html",
     "panel": 1,
     "action": "open"
    }
   ],
   "layout": "",
   "path": [
    "document-ready"
   ],
   "type": "markdown",
   "content-file": ".guides/content/Document-ready-1501.md",
   "chapter": true,
   "reset": [
    "document-ready"
   ],
   "teacherOnly": false
  },
  {
   "id": "d967caca-9a9b-864-1d81-f5bd4d532f45",
   "title": "Introduction to the DOM",
   "files": [
    {
     "path": "#tabs",
     "action": "close"
    },
    {
     "path": "introduction-dom/index.html",
     "panel": 0,
     "action": "open"
    },
    {
     "path": "#preview: introduction-dom/index.html",
     "panel": 1,
     "action": "open"
    }
   ],
   "layout": "",
   "path": [
    "introduction-dom"
   ],
   "type": "markdown",
   "content-file": ".guides/content/Introduction-to-the-DOM-d967.md",
   "chapter": true,
   "reset": [
    "introduction-dom"
   ],
   "teacherOnly": false
  },
  {
   "id": "80f164b7-741b-614f-89e3-6c4f49e1627a",
   "title": "getElementById",
   "files": [],
   "layout": "",
   "path": [
    "introduction-dom"
   ],
   "type": "markdown",
   "content-file": ".guides/content/getElementById-80f1.md",
   "chapter": false,
   "reset": [],
   "teacherOnly": false
  },
  {
   "id": "d90d1028-1ce7-99b4-4b4b-683b3013238",
   "title": "querySelector",
   "files": [
    {
     "path": "#tabs",
     "action": "close"
    },
    {
     "path": "introduction-dom/queryselector.html",
     "panel": 0,
     "action": "open"
    },
    {
     "path": "#preview: introduction-dom/queryselector.html",
     "panel": 1,
     "action": "open"
    }
   ],
   "layout": "",
   "path": [
    "introduction-dom"
   ],
   "type": "markdown",
   "content-file": ".guides/content/querySelector-d90d.md",
   "chapter": false,
   "reset": [],
   "teacherOnly": false
  },
  {
   "id": "f90588c6-2d96-c015-5390-7cb8fe0dd9e5",
   "title": "DOM/CSS manipulation in JS",
   "files": [
    {
     "path": "#tabs",
     "action": "close"
    },
    {
     "path": ".guides/dom-manip/index.html",
     "panel": 0,
     "action": "open"
    },
    {
     "path": "#preview: .guides/dom-manip/index.html",
     "panel": 1,
     "action": "open"
    }
   ],
   "layout": "",
   "path": [
    "dom-manipulation"
   ],
   "type": "markdown",
   "content-file": ".guides/content/DOM-CSS-manipulation-in-JS-f905.md",
   "chapter": true,
   "reset": [
    "dom-manipulation"
   ],
   "teacherOnly": false
  },
  {
   "id": "11e580e6-4bc0-2ff6-f48b-22eb86417f89",
   "title": "Creating elements",
   "files": [
    {
     "path": "#tabs",
     "action": "close"
    },
    {
     "path": ".guides/dom-manip/index-adding.html",
     "panel": 0,
     "action": "open"
    },
    {
     "path": "#preview: .guides/dom-manip/index-adding.html",
     "panel": 1,
     "action": "open"
    }
   ],
   "layout": "",
   "path": [],
   "type": "markdown",
   "content-file": ".guides/content/Creating-elements-11e5.md",
   "chapter": false,
   "reset": [],
   "teacherOnly": false
  },
  {
   "id": "2de7fd07-afa2-938-7662-aca56d77c2a1",
   "title": "Removing elements",
   "files": [
    {
     "path": "#tabs",
     "action": "close"
    },
    {
     "path": ".guides/dom-manip/index-removing.html",
     "panel": 0,
     "action": "open"
    },
    {
     "path": "#preview: .guides/dom-manip/index-removing.html",
     "panel": 1,
     "action": "open"
    }
   ],
   "layout": "",
   "path": [],
   "type": "markdown",
   "content-file": ".guides/content/Removing-elements-2de7.md",
   "chapter": false,
   "reset": [],
   "teacherOnly": false
  },
  {
   "id": "ade3ede5-63c-573b-9f11-174d3cd981a7",
   "title": "Altering properties",
   "files": [
    {
     "path": "#tabs",
     "action": "close"
    },
    {
     "path": ".guides/dom-manip/index-altering.html",
     "panel": 0,
     "action": "open"
    },
    {
     "path": "#preview: .guides/dom-manip/index-altering.html",
     "panel": 1,
     "action": "open"
    }
   ],
   "layout": "",
   "path": [],
   "type": "markdown",
   "content-file": ".guides/content/Altering-properties-ade3.md",
   "chapter": false,
   "reset": [],
   "teacherOnly": false
  },
  {
   "id": "9be742ef-4796-d8de-f715-24afe12cd2ff",
   "title": "Altering styles",
   "files": [
    {
     "path": "#tabs",
     "action": "close"
    },
    {
     "path": ".guides/dom-manip/index-styles.html",
     "panel": 0,
     "action": "open"
    },
    {
     "path": "#preview: .guides/dom-manip/index-styles.html",
     "panel": 1,
     "action": "open"
    }
   ],
   "layout": "",
   "path": [],
   "type": "markdown",
   "content-file": ".guides/content/Altering-styles-9be7.md",
   "chapter": false,
   "reset": [],
   "teacherOnly": false
  },
  {
   "id": "7974f522-c205-ff96-bd4-5369905f19c4",
   "title": "Adding CSS classes",
   "files": [
    {
     "path": "#tabs",
     "action": "close"
    },
    {
     "path": ".guides/dom-manip/index-add-class.html",
     "panel": 0,
     "action": "open"
    },
    {
     "path": "#preview: .guides/dom-manip/index-add-class.html",
     "panel": 1,
     "action": "open"
    }
   ],
   "layout": "",
   "path": [],
   "type": "markdown",
   "content-file": ".guides/content/Adding-CSS-classes-7974.md",
   "chapter": false,
   "reset": [],
   "teacherOnly": false
  },
  {
   "id": "2697fc48-218d-3dfe-205f-f3e0132727da",
   "title": "Removing CSS classes from elements",
   "files": [
    {
     "path": "#tabs",
     "action": "close"
    },
    {
     "path": ".guides/dom-manip/index-remove-class.html",
     "panel": 0,
     "action": "open"
    },
    {
     "path": "#preview: .guides/dom-manip/index-remove-class.html",
     "panel": 1,
     "action": "open"
    }
   ],
   "layout": "",
   "path": [],
   "type": "markdown",
   "content-file": ".guides/content/Removing-CSS-classes-from-elements-2697.md",
   "chapter": false,
   "reset": [],
   "teacherOnly": false
  },
  {
   "id": "709a8948-cbea-c050-ba79-6ae6621c597",
   "title": "Introduction to jQuery",
   "files": [
    {
     "path": "#tabs",
     "action": "close"
    }
   ],
   "layout": "1-panel",
   "path": [],
   "type": "markdown",
   "content-file": ".guides/content/Introduction-to-jQuery-709a.md",
   "chapter": true,
   "reset": [],
   "teacherOnly": false
  },
  {
   "id": "6077186d-6760-b1f8-6500-96f63d7dc33e",
   "title": "Loading jQuery",
   "files": [],
   "layout": "",
   "path": [],
   "type": "markdown",
   "content-file": ".guides/content/Loading-jQuery-6077.md",
   "chapter": false,
   "reset": [],
   "teacherOnly": false
  },
  {
   "id": "20bcb6dd-9f7-471-d14c-b7e07bd45fae",
   "title": "First steps",
   "files": [],
   "path": [],
   "type": "markdown",
   "content-file": ".guides/content/First-steps-20bc.md",
   "chapter": false,
   "reset": [],
   "teacherOnly": false
  },
  {
   "id": "23017d1d-ba17-624d-7e48-dfbc698e928",
   "title": "Chaining",
   "files": [],
   "path": [],
   "type": "markdown",
   "content-file": ".guides/content/Chaining-2301.md",
   "chapter": false,
   "reset": [],
   "teacherOnly": false
  },
  {
   "id": "d64517eb-c3ed-46a-1773-86a1e5a1d637",
   "title": "Silent errors",
   "files": [],
   "path": [],
   "type": "markdown",
   "content-file": ".guides/content/Silent-errors-d645.md",
   "chapter": false,
   "reset": [],
   "teacherOnly": false
  },
  {
   "id": "325ba7b9-b558-29f4-f0bc-e452c9761384",
   "title": "jQuery DOM and CSS manipulations",
   "files": [
    {
     "path": "#tabs",
     "action": "close"
    },
    {
     "path": ".guides/dom-manip/index.html",
     "panel": 0,
     "action": "open"
    },
    {
     "path": "#preview: .guides/dom-manip/index.html",
     "panel": 1,
     "action": "open"
    }
   ],
   "layout": "3-cell",
   "path": [
    "dom-manipulation"
   ],
   "type": "markdown",
   "content-file": ".guides/content/jQuery-DOM-and-CSS-manipulations-325b.md",
   "chapter": true,
   "reset": [],
   "teacherOnly": false
  },
  {
   "id": "2287cd71-360d-1b-7c79-92053e644f24",
   "title": "Creating elements",
   "files": [
    {
     "path": "#tabs",
     "action": "close"
    },
    {
     "path": ".guides/dom-manip/index-adding.html",
     "panel": 0,
     "action": "open"
    },
    {
     "path": "#preview: .guides/dom-manip/index-adding.html",
     "panel": 1,
     "action": "open"
    }
   ],
   "layout": "",
   "path": [],
   "type": "markdown",
   "content-file": ".guides/content/Creating-elements-2287.md",
   "chapter": false,
   "reset": [],
   "teacherOnly": false
  },
  {
   "id": "8d33d74c-7180-3b-5a94-63a8db1ba304",
   "title": "Removing elements",
   "files": [
    {
     "path": "#tabs",
     "action": "close"
    },
    {
     "path": ".guides/dom-manip/index-removing.html",
     "panel": 0,
     "action": "open"
    },
    {
     "path": "#preview: .guides/dom-manip/index-removing.html",
     "panel": 1,
     "action": "open"
    }
   ],
   "layout": "",
   "path": [],
   "type": "markdown",
   "content-file": ".guides/content/Removing-elements-8d33.md",
   "chapter": false,
   "reset": [],
   "teacherOnly": false
  },
  {
   "id": "6718ec55-e6e2-4220-6945-2bd7bd5877df",
   "title": "Altering properties",
   "files": [
    {
     "path": "#tabs",
     "action": "close"
    },
    {
     "path": ".guides/dom-manip/index-altering.html",
     "panel": 0,
     "action": "open"
    },
    {
     "path": "#preview: .guides/dom-manip/index-altering.html",
     "panel": 1,
     "action": "open"
    }
   ],
   "layout": "",
   "path": [],
   "type": "markdown",
   "content-file": ".guides/content/Altering-properties-6718.md",
   "chapter": false,
   "reset": [],
   "teacherOnly": false
  },
  {
   "id": "117f3ff2-aacc-3d3f-ba0f-1d4b4b6a6b9b",
   "title": "Altering styles",
   "files": [
    {
     "path": "#tabs",
     "action": "close"
    },
    {
     "path": ".guides/dom-manip/index-styles.html",
     "panel": 0,
     "action": "open"
    },
    {
     "path": "#preview: .guides/dom-manip/index-styles.html",
     "panel": 1,
     "action": "open"
    }
   ],
   "layout": "",
   "path": [],
   "type": "markdown",
   "content-file": ".guides/content/Altering-styles-117f.md",
   "chapter": false,
   "reset": [],
   "teacherOnly": false
  },
  {
   "id": "b3096789-241f-1bce-5074-517e8e465c7f",
   "title": "Adding CSS classes",
   "files": [
    {
     "path": "#tabs",
     "action": "close"
    },
    {
     "path": ".guides/dom-manip/index-add-class.html",
     "panel": 0,
     "action": "open"
    },
    {
     "path": "#preview: .guides/dom-manip/index-add-class.html",
     "panel": 1,
     "action": "open"
    }
   ],
   "layout": "",
   "path": [],
   "type": "markdown",
   "content-file": ".guides/content/Adding-CSS-classes-b309.md",
   "chapter": false,
   "reset": [],
   "teacherOnly": false
  },
  {
   "id": "a9ba6f3-9d1c-2bf1-f2c7-c798961ad215",
   "title": "Removing CSS classes",
   "files": [
    {
     "path": "#tabs",
     "action": "close"
    },
    {
     "path": ".guides/dom-manip/index-remove-class.html",
     "panel": 0,
     "action": "open"
    },
    {
     "path": "#preview: .guides/dom-manip/index-remove-class.html",
     "panel": 1,
     "action": "open"
    }
   ],
   "layout": "",
   "path": [],
   "type": "markdown",
   "content-file": ".guides/content/Removing-CSS-classes-a9ba.md",
   "chapter": false,
   "reset": [],
   "teacherOnly": false
  },
  {
   "id": "2a06e06e-8ed3-4e68-47fb-a56cb0356248",
   "title": "Final Challenge",
   "files": [
    {
     "path": "#tabs",
     "action": "close"
    },
    {
     "path": "final-challenge/challenge.html",
     "panel": 0,
     "action": "open"
    },
    {
     "path": "#preview: final-challenge/challenge.html",
     "panel": 1,
     "action": "open"
    }
   ],
   "layout": "3-cell-tree",
   "path": [
    "final-challenge"
   ],
   "type": "markdown",
   "content-file": ".guides/content/Final-Challenge-2a06.md",
   "chapter": true,
   "reset": [],
   "teacherOnly": false
  },
  {
   "id": "3d5f8d9a-50e-26f9-d662-f4d46612b17",
   "title": "That's all folks",
   "files": [
    {
     "path": "#tabs",
     "action": "close"
    }
   ],
   "layout": "1-panel",
   "path": [],
   "type": "markdown",
   "content-file": ".guides/content/That-s-all-folks-3d5f.md",
   "chapter": true,
   "reset": [],
   "teacherOnly": false
  }
 ],
 "theme": "light",
 "scripts": [],
 "lexikonTopic": ""
}